MANIFEST.in
README.md
VERSION
requirements.txt
setup.py
lambda_image_utils_prebuilt/__init__.py
lambda_image_utils_prebuilt/unpack.py
lambda_image_utils_prebuilt.egg-info/PKG-INFO
lambda_image_utils_prebuilt.egg-info/SOURCES.txt
lambda_image_utils_prebuilt.egg-info/dependency_links.txt
lambda_image_utils_prebuilt.egg-info/entry_points.txt
lambda_image_utils_prebuilt.egg-info/requires.txt
lambda_image_utils_prebuilt.egg-info/top_level.txt