Metadata-Version: 1.1
Name: lambda-image-utils-prebuilt
Version: 0.0.20
Summary: Prebuilt dependencies for running some common image utilities in AWS Lambda
Home-page: https://github.com/jonathanporta/lambda_image_utils_prebuilt
Author: Jonathan Porta
Author-email: jonathan@jonathanPorta.com
License: MIT
Keywords: lambda opencv dlib aws_lambda
Platform: UNKNOWN
Classifier: Development Status :: 5 - Production/Stable
Classifier: Intended Audience :: Developers
Classifier: Topic :: Software Development :: Build Tools
Classifier: License :: OSI Approved :: MIT License
Classifier: Programming Language :: Python :: 3.6
